cdk_budget_notifier/__init__.py
cdk_budget_notifier/py.typed
cdk_budget_notifier/_jsii/__init__.py
cdk_budget_notifier/_jsii/aws_budget_notifier@0.3.45.jsii.tgz
cdk_budget_notifier-0.3.45.dist-info/LICENSE
cdk_budget_notifier-0.3.45.dist-info/METADATA
cdk_budget_notifier-0.3.45.dist-info/WHEEL
cdk_budget_notifier-0.3.45.dist-info/top_level.txt
cdk_budget_notifier-0.3.45.dist-info/RECORD
